bigcodec/__init__.py
bigcodec/hf_model.py
bigcodec/modules.py
bigcodec-0.0.3.dist-info/METADATA
bigcodec-0.0.3.dist-info/WHEEL
bigcodec-0.0.3.dist-info/top_level.txt
bigcodec-0.0.3.dist-info/RECORD
